importer/__init__.py
importer/import_constants.py
constantsimportertest-1.0.0.dist-info/METADATA
constantsimportertest-1.0.0.dist-info/WHEEL
constantsimportertest-1.0.0.dist-info/top_level.txt
constantsimportertest-1.0.0.dist-info/RECORD
